audio_controller/__init__.py
audio_controller/player.py
audiocontroller-0.1.0.dist-info/LICENSE
audiocontroller-0.1.0.dist-info/METADATA
audiocontroller-0.1.0.dist-info/WHEEL
audiocontroller-0.1.0.dist-info/top_level.txt
audiocontroller-0.1.0.dist-info/RECORD
