Metadata-Version: 2.1
Name: audiocontroller
Version: 0.1.0
Summary: A simple Python library to control audio playback (play, pause, stop)
Home-page: https://github.com/Harshitha-atra/audio-control-lib.git
Author: Harshitha
Author-email: harshitha.atra1306@gmail.com
Classifier: Programming Language :: Python :: 3
Classifier: License :: OSI Approved :: MIT License
Classifier: Operating System :: OS Independent
Requires-Python: >=3.6
License-File: LICENSE
